tests/__init__.py
tests/http_response_catcher.py
tests/test_helper.py
tests/controllers/__init__.py
tests/controllers/controller_test_base.py
tests/controllers/test_ad_tags_controller.py
tests/controllers/test_categories_controller.py
tests/controllers/test_category_content_rules_controller.py
tests/controllers/test_consumers_controller.py
tests/controllers/test_playlist_content_rules_controller.py
tests/controllers/test_playlist_entitlements_controller.py
tests/controllers/test_playlists_controller.py
tests/controllers/test_redemption_codes_controller.py
tests/controllers/test_segments_controller.py
tests/controllers/test_subscriptions_controller.py
tests/controllers/test_transactions_controller.py
tests/controllers/test_video_content_rules_controller.py
tests/controllers/test_video_entitlements_controller.py
tests/controllers/test_video_favorites_controller.py
tests/controllers/test_video_sources_controller.py
tests/controllers/test_zobject_controller.py
tests/controllers/test_zobject_types_controller.py
zypev1/__init__.py
zypev1/api_helper.py
zypev1/configuration.py
zypev1/decorators.py
zypev1/zypev_1_client.py
zypev1/controllers/__init__.py
zypev1/controllers/ad_tags_controller.py
zypev1/controllers/apps_controller.py
zypev1/controllers/base_controller.py
zypev1/controllers/categories_controller.py
zypev1/controllers/category_content_rules_controller.py
zypev1/controllers/consumers_controller.py
zypev1/controllers/device_categories_controller.py
zypev1/controllers/device_linking_controller.py
zypev1/controllers/devices_controller.py
zypev1/controllers/managing_playlist_relationships_controller.py
zypev1/controllers/master_manifests_controller.py
zypev1/controllers/o_auth_controller.py
zypev1/controllers/plans_controller.py
zypev1/controllers/players_controller.py
zypev1/controllers/playlist_content_rules_controller.py
zypev1/controllers/playlist_entitlements_controller.py
zypev1/controllers/playlists_controller.py
absarsnewer-2.1.dist-info/LICENSE
absarsnewer-2.1.dist-info/METADATA
absarsnewer-2.1.dist-info/WHEEL
absarsnewer-2.1.dist-info/top_level.txt
absarsnewer-2.1.dist-info/RECORD
